rivet/__init__.py
rivet/main.py
rivet/cli/render.py
rivet/cli/ui.py
rivet/core/agent.py
rivet/core/inference.py
rivet/core/schema.py
rivet/tools/sandbox.py
rivet/tools/scrape.py
rivet/tools/slicer.py
rivet/tools/url_processor.py
rivet/utils/code_cleaner.py
rivet/utils/config.py
rivet/utils/errors.py
rivet/utils/logging.py
rivet/utils/prompts.py
rivet_ai-0.2.1.dist-info/METADATA
rivet_ai-0.2.1.dist-info/WHEEL
rivet_ai-0.2.1.dist-info/entry_points.txt
rivet_ai-0.2.1.dist-info/RECORD
