Metadata-Version: 2.4
Name: rivet-ai
Version: 0.2.1
Summary: Add your description here
Author-email: Yash Ghogre <yashghogre100@gmail.com>
License: MIT
Classifier: Operating System :: OS Independent
Classifier: Programming Language :: Python :: 3
Requires-Python: >=3.12
Requires-Dist: beautifulsoup4>=4.14.3
Requires-Dist: docker>=7.1.0
Requires-Dist: httpx>=0.28.1
Requires-Dist: langgraph>=1.0.4
Requires-Dist: langsmith>=0.4.49
Requires-Dist: openai>=2.9.0
Requires-Dist: platformdirs>=4.5.0
Requires-Dist: pydantic>=2.12.5
Requires-Dist: pytest-asyncio>=1.3.0
Requires-Dist: pytest>=9.0.1
Requires-Dist: pyyaml>=6.0.3
Requires-Dist: rich>=14.2.0
Requires-Dist: typer>=0.20.0
